tornado_transmute/__init__.py
tornado_transmute/handler.py
tornado_transmute/route_set.py
tornado_transmute/swagger.py
tornado_transmute/url.py
tornado_transmute/tests/__init__.py
tornado_transmute/tests/conftest.py
tornado_transmute/tests/example.py
tornado_transmute/tests/test_handle.py
tornado_transmute-0.0.4.dist-info/METADATA
tornado_transmute-0.0.4.dist-info/RECORD
tornado_transmute-0.0.4.dist-info/WHEEL
tornado_transmute-0.0.4.dist-info/top_level.txt
